MANIFEST.in
README.rst
setup.py
aliyunsdkslb/__init__.py
aliyunsdkslb/request/__init__.py
aliyunsdkslb/request/v20140515/AddAccessControlListEntryRequest.py
aliyunsdkslb/request/v20140515/AddBackendServersRequest.py
aliyunsdkslb/request/v20140515/AddListenerWhiteListItemRequest.py
aliyunsdkslb/request/v20140515/AddTagsRequest.py
aliyunsdkslb/request/v20140515/AddVServerGroupBackendServersRequest.py
aliyunsdkslb/request/v20140515/CreateAccessControlListRequest.py
aliyunsdkslb/request/v20140515/CreateLoadBalancerHTTPListenerRequest.py
aliyunsdkslb/request/v20140515/CreateLoadBalancerHTTPSListenerRequest.py
aliyunsdkslb/request/v20140515/CreateLoadBalancerRequest.py
aliyunsdkslb/request/v20140515/CreateLoadBalancerTCPListenerRequest.py
aliyunsdkslb/request/v20140515/CreateLoadBalancerUDPListenerRequest.py
aliyunsdkslb/request/v20140515/CreateMasterSlaveServerGroupRequest.py
aliyunsdkslb/request/v20140515/CreateMasterSlaveVServerGroupRequest.py
aliyunsdkslb/request/v20140515/CreateRulesRequest.py
aliyunsdkslb/request/v20140515/CreateVServerGroupRequest.py
aliyunsdkslb/request/v20140515/DeleteAccessControlListRequest.py
aliyunsdkslb/request/v20140515/DeleteCACertificateRequest.py
aliyunsdkslb/request/v20140515/DeleteLoadBalancerListenerRequest.py
aliyunsdkslb/request/v20140515/DeleteLoadBalancerRequest.py
aliyunsdkslb/request/v20140515/DeleteMasterSlaveServerGroupRequest.py
aliyunsdkslb/request/v20140515/DeleteMasterSlaveVServerGroupRequest.py
aliyunsdkslb/request/v20140515/DeleteRulesRequest.py
aliyunsdkslb/request/v20140515/DeleteServerCertificateRequest.py
aliyunsdkslb/request/v20140515/DeleteVServerGroupRequest.py
aliyunsdkslb/request/v20140515/DescribeAccessControlListAttributeRequest.py
aliyunsdkslb/request/v20140515/DescribeAccessControlListsRequest.py
aliyunsdkslb/request/v20140515/DescribeCACertificatesRequest.py
aliyunsdkslb/request/v20140515/DescribeHealthStatusRequest.py
aliyunsdkslb/request/v20140515/DescribeListenerAccessControlAttributeRequest.py
dd_aliyun_python_sdk_slb.egg-info/PKG-INFO
dd_aliyun_python_sdk_slb.egg-info/SOURCES.txt
dd_aliyun_python_sdk_slb.egg-info/dependency_links.txt
dd_aliyun_python_sdk_slb.egg-info/requires.txt
dd_aliyun_python_sdk_slb.egg-info/top_level.txt